src/__init__.py
src/calculate.py
css_specificity-0.1.3.dist-info/LICENSE
css_specificity-0.1.3.dist-info/METADATA
css_specificity-0.1.3.dist-info/WHEEL
css_specificity-0.1.3.dist-info/RECORD
