Metadata-Version: 2.3
Name: css_specificity
Version: 0.1.3
Summary: A Python library for calculating the specificity of CSS selectors
License: MIT
Author: Devlink42
Author-email: 8506859-devlink42@users.noreply.gitlab.com
Requires-Python: >=3.9
Classifier: License :: OSI Approved :: MIT License
Classifier: Operating System :: OS Independent
Classifier: Programming Language :: Python :: 3
Classifier: Programming Language :: Python :: 3.9
Classifier: Programming Language :: Python :: 3.10
Classifier: Programming Language :: Python :: 3.11
Classifier: Programming Language :: Python :: 3.12
Classifier: Programming Language :: Python :: 3.13
Requires-Dist: black (>=25.1.0,<26.0.0)
Requires-Dist: tinycss2 (>=1.4.0,<2.0.0)
Project-URL: CSS Specificity Doc, https://www.w3.org/TR/selectors-4/#specificity-rules
Project-URL: Repository, https://gitlab.com/devlink42/css_specificity
